indian_names/__init__.py
indian_names/first.female.names
indian_names/first.male.names
indian_names/last.names
indian_names/main.py
indian_names-0.3.dist-info/LICENSE
indian_names-0.3.dist-info/METADATA
indian_names-0.3.dist-info/WHEEL
indian_names-0.3.dist-info/entry_points.txt
indian_names-0.3.dist-info/top_level.txt
indian_names-0.3.dist-info/RECORD
