Metadata-Version: 2.1
Name: indian-names
Version: 0.3
Summary: Generate random names of Indian origin
Home-page: https://github.com/ByteBaker/indian-names
Author: Shraddha Kishan Tripathi
License: BSD 3-Clause License
Platform: UNKNOWN
Classifier: Development Status :: 5 - Production/Stable
Classifier: Environment :: Console
Classifier: Operating System :: OS Independent
Classifier: Programming Language :: Python :: 3.6
Requires-Python: >=3.6
